{"file_metadata": {"source": "Frankfurter Exchange Rates API", "fetch_time": "2026-04-07 22:35:41", "base_currency": "USD", "amount": 1.0, "start_date": "2000-01-01", "end_date": "", "file_date": "2011-05-25", "currency_codes": ["AUD", "BGN", "BRL", "CAD", "CHF", "CNY", "CZK", "DKK", "EUR", "GBP", "HKD", "HRK", "HUF", "IDR", "ILS", "INR", "JPY", "KRW", "LTL", "LVL", "MXN", "MYR", "NOK", "NZD", "PHP", "PLN", "RON", "RUB", "SEK", "SGD", "THB", "TRY", "ZAR"], "count_of_currencies": 33}, "data": {"AUD": 0.95238, "BGN": 1.3901, "BRL": 1.6305, "CAD": 0.97861, "CHF": 0.87597, "CNY": 6.4935, "CZK": 17.4689, "DKK": 5.3002, "EUR": 0.71078, "GBP": 0.61639, "HKD": 7.7812, "HRK": 5.2918, "HUF": 191.95, "IDR": 8595, "ILS": 3.4982, "INR": 45.33, "JPY": 82.07, "KRW": 1101.96, "LTL": 2.4542, "LVL": 0.50416, "MXN": 11.718, "MYR": 3.0625, "NOK": 5.5612, "NZD": 1.2561, "PHP": 43.548, "PLN": 2.8202, "RON": 2.9387, "RUB": 28.438, "SEK": 6.3366, "SGD": 1.2479, "THB": 30.45, "TRY": 1.6066, "ZAR": 7.058}}