{"file_metadata": {"source": "Frankfurter Exchange Rates API", "fetch_time": "2026-04-07 22:35:41", "base_currency": "USD", "amount": 1.0, "start_date": "2000-01-01", "end_date": "", "file_date": "2004-11-08", "currency_codes": ["AUD", "BGN", "CAD", "CHF", "CYP", "CZK", "DKK", "EEK", "EUR", "GBP", "HKD", "HUF", "ISK", "JPY", "KRW", "LTL", "LVL", "MTL", "NOK", "NZD", "PLN", "ROL", "SEK", "SGD", "SIT", "SKK", "TRL", "ZAR"], "count_of_currencies": 28}, "data": {"AUD": 1.3185, "BGN": 1.5142, "CAD": 1.1953, "CHF": 1.1834, "CYP": 0.44662, "CZK": 24.325, "DKK": 5.7541, "EEK": 12.1132, "EUR": 0.77417, "GBP": 0.53956, "HKD": 7.7763, "HUF": 189.88, "ISK": 67.539, "JPY": 105.72, "KRW": 1105.3, "LTL": 2.6731, "LVL": 0.52559, "MTL": 0.33406, "NOK": 6.3413, "NZD": 1.4396, "PLN": 3.296, "ROL": 31485, "SEK": 7.0362, "SGD": 1.6529, "SIT": 185.63, "SKK": 30.797, "TRL": 1455524, "ZAR": 6.1868}}