{"file_metadata": {"source": "Frankfurter Exchange Rates API", "fetch_time": "2026-04-07 22:35:41", "base_currency": "USD", "amount": 1.0, "start_date": "2000-01-01", "end_date": "", "file_date": "2012-07-23", "currency_codes": ["AUD", "BGN", "BRL", "CAD", "CHF", "CNY", "CZK", "DKK", "EUR", "GBP", "HKD", "HRK", "HUF", "IDR", "ILS", "INR", "JPY", "KRW", "LTL", "LVL", "MXN", "MYR", "NOK", "NZD", "PHP", "PLN", "RON", "RUB", "SEK", "SGD", "THB", "TRY", "ZAR"], "count_of_currencies": 33}, "data": {"AUD": 0.97348, "BGN": 1.6157, "BRL": 2.0403, "CAD": 1.0173, "CHF": 0.99215, "CNY": 6.386, "CZK": 21.131, "DKK": 6.1459, "EUR": 0.8261, "GBP": 0.6442, "HKD": 7.757, "HRK": 6.1981, "HUF": 238.2, "IDR": 9480, "ILS": 4.0416, "INR": 55.974, "JPY": 78.249, "KRW": 1149.18, "LTL": 2.8524, "LVL": 0.57513, "MXN": 13.5246, "MYR": 3.1719, "NOK": 6.0975, "NZD": 1.264, "PHP": 42.088, "PLN": 3.467, "RON": 3.8199, "RUB": 32.624, "SEK": 6.9812, "SGD": 1.261, "THB": 31.78, "TRY": 1.821, "ZAR": 8.4638}}