{"file_metadata": {"source": "Frankfurter Exchange Rates API", "fetch_time": "2026-04-07 22:35:41", "base_currency": "USD", "amount": 1.0, "start_date": "2000-01-01", "end_date": "", "file_date": "2007-12-17", "currency_codes": ["AUD", "BGN", "CAD", "CHF", "CNY", "CYP", "CZK", "DKK", "EEK", "EUR", "GBP", "HKD", "HRK", "HUF", "IDR", "ISK", "JPY", "KRW", "LTL", "LVL", "MTL", "MYR", "NOK", "NZD", "PHP", "PLN", "RON", "RUB", "SEK", "SGD", "SKK", "THB", "TRY", "ZAR"], "count_of_currencies": 34}, "data": {"AUD": 1.1649, "BGN": 1.3589, "CAD": 1.0117, "CHF": 1.1542, "CNY": 7.3873, "CYP": 0.40664, "CZK": 18.3388, "DKK": 5.1847, "EEK": 10.871, "EUR": 0.69478, "GBP": 0.49587, "HKD": 7.798, "HRK": 5.081, "HUF": 176.63, "IDR": 9415, "ISK": 63.045, "JPY": 113.33, "KRW": 933.6, "LTL": 2.3989, "LVL": 0.48399, "MTL": 0.29827, "MYR": 3.3405, "NOK": 5.543, "NZD": 1.323, "PHP": 41.43, "PLN": 2.5134, "RON": 2.4699, "RUB": 24.721, "SEK": 6.5722, "SGD": 1.4598, "SKK": 23.313, "THB": 30.39, "TRY": 1.1895, "ZAR": 6.902}}