{"file_metadata": {"source": "Frankfurter Exchange Rates API", "fetch_time": "2026-04-07 22:35:41", "base_currency": "USD", "amount": 1.0, "start_date": "2000-01-01", "end_date": "", "file_date": "2010-12-29", "currency_codes": ["AUD", "BGN", "BRL", "CAD", "CHF", "CNY", "CZK", "DKK", "EEK", "EUR", "GBP", "HKD", "HRK", "HUF", "IDR", "INR", "JPY", "KRW", "LTL", "LVL", "MXN", "MYR", "NOK", "NZD", "PHP", "PLN", "RON", "RUB", "SEK", "SGD", "THB", "TRY", "ZAR"], "count_of_currencies": 33}, "data": {"AUD": 0.98774, "BGN": 1.4889, "BRL": 1.6845, "CAD": 1.0014, "CHF": 0.95029, "CNY": 6.6212, "CZK": 19.2319, "DKK": 5.6736, "EEK": 11.9112, "EUR": 0.76127, "GBP": 0.65005, "HKD": 7.782, "HRK": 5.6218, "HUF": 212.7, "IDR": 9000, "INR": 45.033, "JPY": 82.21, "KRW": 1142.33, "LTL": 2.6285, "LVL": 0.54027, "MXN": 12.384, "MYR": 3.0845, "NOK": 5.9447, "NZD": 1.3149, "PHP": 43.85, "PLN": 3.0197, "RON": 3.2724, "RUB": 30.447, "SEK": 6.8426, "SGD": 1.2974, "THB": 30.167, "TRY": 1.564, "ZAR": 6.6881}}