{"file_metadata": {"source": "Frankfurter Exchange Rates API", "fetch_time": "2026-04-07 22:35:41", "base_currency": "USD", "amount": 1.0, "start_date": "2000-01-01", "end_date": "", "file_date": "2009-01-07", "currency_codes": ["AUD", "BGN", "BRL", "CAD", "CHF", "CNY", "CZK", "DKK", "EEK", "EUR", "GBP", "HKD", "HRK", "HUF", "IDR", "INR", "JPY", "KRW", "LTL", "LVL", "MXN", "MYR", "NOK", "NZD", "PHP", "PLN", "RON", "RUB", "SEK", "SGD", "THB", "TRY", "ZAR"], "count_of_currencies": 33}, "data": {"AUD": 1.3851, "BGN": 1.4386, "BRL": 2.205, "CAD": 1.1814, "CHF": 1.1038, "CNY": 6.834, "CZK": 19.2107, "DKK": 5.4816, "EEK": 11.5091, "EUR": 0.73556, "GBP": 0.66517, "HKD": 7.7527, "HRK": 5.371, "HUF": 195.76, "IDR": 10850, "INR": 48.815, "JPY": 93.25, "KRW": 1309.4, "LTL": 2.5398, "LVL": 0.51997, "MXN": 13.44, "MYR": 3.5005, "NOK": 6.9081, "NZD": 1.671, "PHP": 46.451, "PLN": 2.9236, "RON": 3.0154, "RUB": 29.354, "SEK": 7.7796, "SGD": 1.4704, "THB": 34.83, "TRY": 1.5206, "ZAR": 9.3527}}