{"file_metadata": {"source": "Frankfurter Exchange Rates API", "fetch_time": "2026-04-07 22:35:41", "base_currency": "USD", "amount": 1.0, "start_date": "2000-01-01", "end_date": "", "file_date": "2020-11-02", "currency_codes": ["AUD", "BGN", "BRL", "CAD", "CHF", "CNY", "CZK", "DKK", "EUR", "GBP", "HKD", "HRK", "HUF", "IDR", "ILS", "INR", "ISK", "JPY", "KRW", "MXN", "MYR", "NOK", "NZD", "PHP", "PLN", "RON", "RUB", "SEK", "SGD", "THB", "TRY", "ZAR"], "count_of_currencies": 32}, "data": {"AUD": 1.4189, "BGN": 1.6785, "BRL": 5.7429, "CAD": 1.3273, "CHF": 0.91787, "CNY": 6.6909, "CZK": 23.284, "DKK": 6.3899, "EUR": 0.85822, "GBP": 0.77285, "HKD": 7.7521, "HRK": 6.4963, "HUF": 314.32, "IDR": 14646, "ILS": 3.4055, "INR": 74.459, "ISK": 140.32, "JPY": 104.64, "KRW": 1133.38, "MXN": 21.226, "MYR": 4.1575, "NOK": 9.5372, "NZD": 1.5075, "PHP": 48.41, "PLN": 3.9494, "RON": 4.1773, "RUB": 80.45, "SEK": 8.8933, "SGD": 1.3648, "THB": 31.11, "TRY": 8.4391, "ZAR": 16.218}}