{"file_metadata": {"source": "Frankfurter Exchange Rates API", "fetch_time": "2026-04-07 22:35:41", "base_currency": "USD", "amount": 1.0, "start_date": "2000-01-01", "end_date": "", "file_date": "2013-06-27", "currency_codes": ["AUD", "BGN", "BRL", "CAD", "CHF", "CNY", "CZK", "DKK", "EUR", "GBP", "HKD", "HRK", "HUF", "IDR", "ILS", "INR", "JPY", "KRW", "LTL", "LVL", "MXN", "MYR", "NOK", "NZD", "PHP", "PLN", "RON", "RUB", "SEK", "SGD", "THB", "TRY", "ZAR"], "count_of_currencies": 33}, "data": {"AUD": 1.0739, "BGN": 1.5008, "BRL": 2.1808, "CAD": 1.0435, "CHF": 0.94583, "CNY": 6.1489, "CZK": 19.8665, "DKK": 5.7238, "EUR": 0.76734, "GBP": 0.65462, "HKD": 7.7572, "HRK": 5.7198, "HUF": 226.35, "IDR": 9926, "ILS": 3.6357, "INR": 60.2, "JPY": 98.17, "KRW": 1147.57, "LTL": 2.6495, "LVL": 0.53875, "MXN": 13.0538, "MYR": 3.1739, "NOK": 6.0474, "NZD": 1.2769, "PHP": 43.31, "PLN": 3.3151, "RON": 3.4164, "RUB": 32.792, "SEK": 6.7188, "SGD": 1.2634, "THB": 31.12, "TRY": 1.9237, "ZAR": 9.9478}}