{"file_metadata": {"source": "Frankfurter Exchange Rates API", "fetch_time": "2026-04-07 22:35:41", "base_currency": "USD", "amount": 1.0, "start_date": "2000-01-01", "end_date": "", "file_date": "2020-01-16", "currency_codes": ["AUD", "BGN", "BRL", "CAD", "CHF", "CNY", "CZK", "DKK", "EUR", "GBP", "HKD", "HRK", "HUF", "IDR", "ILS", "INR", "ISK", "JPY", "KRW", "MXN", "MYR", "NOK", "NZD", "PHP", "PLN", "RON", "RUB", "SEK", "SGD", "THB", "TRY", "ZAR"], "count_of_currencies": 32}, "data": {"AUD": 1.4428, "BGN": 1.7511, "BRL": 4.165, "CAD": 1.3035, "CHF": 0.9615, "CNY": 6.8795, "CZK": 22.536, "DKK": 6.6908, "EUR": 0.89534, "GBP": 0.76524, "HKD": 7.7726, "HRK": 6.6629, "HUF": 298.9, "IDR": 13630, "ILS": 3.4538, "INR": 70.929, "ISK": 122.66, "JPY": 109.95, "KRW": 1158.45, "MXN": 18.7931, "MYR": 4.0628, "NOK": 8.869, "NZD": 1.5014, "PHP": 50.834, "PLN": 3.7894, "RON": 4.2788, "RUB": 61.608, "SEK": 9.4617, "SGD": 1.3452, "THB": 30.365, "TRY": 5.8522, "ZAR": 14.4354}}