{"file_metadata": {"source": "Frankfurter Exchange Rates API", "fetch_time": "2026-04-07 22:35:41", "base_currency": "USD", "amount": 1.0, "start_date": "2000-01-01", "end_date": "", "file_date": "2008-11-04", "currency_codes": ["AUD", "BGN", "BRL", "CAD", "CHF", "CNY", "CZK", "DKK", "EEK", "EUR", "GBP", "HKD", "HRK", "HUF", "IDR", "ISK", "JPY", "KRW", "LTL", "LVL", "MXN", "MYR", "NOK", "NZD", "PHP", "PLN", "RON", "RUB", "SEK", "SGD", "SKK", "THB", "TRY", "ZAR"], "count_of_currencies": 34}, "data": {"AUD": 1.4473, "BGN": 1.5256, "BRL": 2.147, "CAD": 1.1661, "CHF": 1.1656, "CNY": 6.836, "CZK": 18.8479, "DKK": 5.8058, "EEK": 12.2048, "EUR": 0.78003, "GBP": 0.62988, "HKD": 7.7502, "HRK": 5.5796, "HUF": 202.7, "IDR": 10900, "ISK": 237.91, "JPY": 99.34, "KRW": 1276.0, "LTL": 2.6933, "LVL": 0.5532, "MXN": 12.6, "MYR": 3.5275, "NOK": 6.6782, "NZD": 1.6461, "PHP": 48.3, "PLN": 2.7509, "RON": 2.8744, "RUB": 26.963, "SEK": 7.7206, "SGD": 1.4731, "SKK": 23.661, "THB": 34.945, "TRY": 1.5116, "ZAR": 9.8575}}