{"file_metadata": {"source": "Frankfurter Exchange Rates API", "fetch_time": "2026-04-07 22:35:41", "base_currency": "USD", "amount": 1.0, "start_date": "2000-01-01", "end_date": "", "file_date": "2025-03-06", "currency_codes": ["AUD", "BGN", "BRL", "CAD", "CHF", "CNY", "CZK", "DKK", "EUR", "GBP", "HKD", "HUF", "IDR", "ILS", "INR", "ISK", "JPY", "KRW", "MXN", "MYR", "NOK", "NZD", "PHP", "PLN", "RON", "SEK", "SGD", "THB", "TRY", "ZAR"], "count_of_currencies": 30}, "data": {"AUD": 1.5781, "BGN": 1.8116, "BRL": 5.751, "CAD": 1.4366, "CHF": 0.88598, "CNY": 7.2478, "CZK": 23.2, "DKK": 6.9093, "EUR": 0.92627, "GBP": 0.77612, "HKD": 7.7734, "HUF": 371.14, "IDR": 16368, "ILS": 3.6146, "INR": 87.08, "ISK": 136.07, "JPY": 147.5, "KRW": 1448.25, "MXN": 20.403, "MYR": 4.4275, "NOK": 10.8522, "NZD": 1.7423, "PHP": 57.358, "PLN": 3.869, "RON": 4.6086, "SEK": 10.1538, "SGD": 1.3326, "THB": 33.715, "TRY": 36.424, "ZAR": 18.3011}}