{"file_metadata": {"source": "Frankfurter Exchange Rates API", "fetch_time": "2026-04-07 22:35:41", "base_currency": "USD", "amount": 1.0, "start_date": "2000-01-01", "end_date": "", "file_date": "2017-12-15", "currency_codes": ["AUD", "BGN", "BRL", "CAD", "CHF", "CNY", "CZK", "DKK", "EUR", "GBP", "HKD", "HRK", "HUF", "IDR", "ILS", "INR", "JPY", "KRW", "MXN", "MYR", "NOK", "NZD", "PHP", "PLN", "RON", "RUB", "SEK", "SGD", "THB", "TRY", "ZAR"], "count_of_currencies": 31}, "data": {"AUD": 1.3029, "BGN": 1.6566, "BRL": 3.3179, "CAD": 1.2765, "CHF": 0.9884, "CNY": 6.6087, "CZK": 21.75, "DKK": 6.3055, "EUR": 0.84703, "GBP": 0.74753, "HKD": 7.8115, "HRK": 6.3921, "HUF": 265.48, "IDR": 13577, "ILS": 3.5265, "INR": 64.042, "JPY": 112.19, "KRW": 1088.2, "MXN": 19.1665, "MYR": 4.0795, "NOK": 8.2863, "NZD": 1.4233, "PHP": 50.422, "PLN": 3.5717, "RON": 3.9244, "RUB": 58.872, "SEK": 8.4349, "SGD": 1.3465, "THB": 32.505, "TRY": 3.8627, "ZAR": 13.3668}}