{"file_metadata": {"source": "Frankfurter Exchange Rates API", "fetch_time": "2026-04-07 22:35:41", "base_currency": "USD", "amount": 1.0, "start_date": "2000-01-01", "end_date": "", "file_date": "2010-05-21", "currency_codes": ["AUD", "BGN", "BRL", "CAD", "CHF", "CNY", "CZK", "DKK", "EEK", "EUR", "GBP", "HKD", "HRK", "HUF", "IDR", "INR", "JPY", "KRW", "LTL", "LVL", "MXN", "MYR", "NOK", "NZD", "PHP", "PLN", "RON", "RUB", "SEK", "SGD", "THB", "TRY", "ZAR"], "count_of_currencies": 33}, "data": {"AUD": 1.2111, "BGN": 1.565, "BRL": 1.8783, "CAD": 1.0728, "CHF": 1.1529, "CNY": 6.8277, "CZK": 20.739, "DKK": 5.9555, "EEK": 12.5203, "EUR": 0.80019, "GBP": 0.69645, "HKD": 7.8056, "HRK": 5.8178, "HUF": 225.12, "IDR": 9265, "INR": 46.945, "JPY": 89.69, "KRW": 1211.32, "LTL": 2.7629, "LVL": 0.56606, "MXN": 13.1061, "MYR": 3.321, "NOK": 6.516, "NZD": 1.4928, "PHP": 46.5, "PLN": 3.3232, "RON": 3.3568, "RUB": 31.244, "SEK": 7.8667, "SGD": 1.4083, "THB": 32.435, "TRY": 1.5873, "ZAR": 7.9382}}