{"file_metadata": {"source": "Frankfurter Exchange Rates API", "fetch_time": "2026-04-07 22:35:41", "base_currency": "USD", "amount": 1.0, "start_date": "2000-01-01", "end_date": "", "file_date": "2008-02-19", "currency_codes": ["AUD", "BGN", "BRL", "CAD", "CHF", "CNY", "CZK", "DKK", "EEK", "EUR", "GBP", "HKD", "HRK", "HUF", "IDR", "ISK", "JPY", "KRW", "LTL", "LVL", "MXN", "MYR", "NOK", "NZD", "PHP", "PLN", "RON", "RUB", "SEK", "SGD", "SKK", "THB", "TRY", "ZAR"], "count_of_currencies": 34}, "data": {"AUD": 1.0842, "BGN": 1.3267, "BRL": 1.7284, "CAD": 1.0064, "CHF": 1.0937, "CNY": 7.158, "CZK": 17.1747, "DKK": 5.0568, "EEK": 10.6136, "EUR": 0.67833, "GBP": 0.51248, "HKD": 7.8008, "HRK": 4.9393, "HUF": 178.79, "IDR": 9170, "ISK": 66.762, "JPY": 107.61, "KRW": 944.45, "LTL": 2.3422, "LVL": 0.4726, "MXN": 10.7371, "MYR": 3.223, "NOK": 5.332, "NZD": 1.2488, "PHP": 40.6, "PLN": 2.4204, "RON": 2.4659, "RUB": 24.527, "SEK": 6.3196, "SGD": 1.4129, "SKK": 22.42, "THB": 31.65, "TRY": 1.1915, "ZAR": 7.6295}}