{"file_metadata": {"source": "Frankfurter Exchange Rates API", "fetch_time": "2026-04-07 22:35:41", "base_currency": "USD", "amount": 1.0, "start_date": "2000-01-01", "end_date": "", "file_date": "2008-06-30", "currency_codes": ["AUD", "BGN", "BRL", "CAD", "CHF", "CNY", "CZK", "DKK", "EEK", "EUR", "GBP", "HKD", "HRK", "HUF", "IDR", "ISK", "JPY", "KRW", "LTL", "LVL", "MXN", "MYR", "NOK", "NZD", "PHP", "PLN", "RON", "RUB", "SEK", "SGD", "SKK", "THB", "TRY", "ZAR"], "count_of_currencies": 34}, "data": {"AUD": 1.0385, "BGN": 1.2407, "BRL": 1.593, "CAD": 1.0113, "CHF": 1.0185, "CNY": 6.8543, "CZK": 15.1567, "DKK": 4.731, "EEK": 9.9255, "EUR": 0.63436, "GBP": 0.50257, "HKD": 7.799, "HRK": 4.5905, "HUF": 149.35, "IDR": 9230, "ISK": 79.561, "JPY": 105.58, "KRW": 1048.1, "LTL": 2.1903, "LVL": 0.44703, "MXN": 10.2955, "MYR": 3.2675, "NOK": 5.0806, "NZD": 1.3088, "PHP": 44.955, "PLN": 2.1259, "RON": 2.31, "RUB": 23.438, "SEK": 6.0075, "SGD": 1.3604, "SKK": 19.1607, "THB": 33.455, "TRY": 1.2258, "ZAR": 7.8296}}