{"file_metadata": {"source": "Frankfurter Exchange Rates API", "fetch_time": "2026-04-07 22:35:41", "base_currency": "USD", "amount": 1.0, "start_date": "2000-01-01", "end_date": "", "file_date": "2011-04-21", "currency_codes": ["AUD", "BGN", "BRL", "CAD", "CHF", "CNY", "CZK", "DKK", "EUR", "GBP", "HKD", "HRK", "HUF", "IDR", "ILS", "INR", "JPY", "KRW", "LTL", "LVL", "MXN", "MYR", "NOK", "NZD", "PHP", "PLN", "RON", "RUB", "SEK", "SGD", "THB", "TRY", "ZAR"], "count_of_currencies": 33}, "data": {"AUD": 0.92992, "BGN": 1.3411, "BRL": 1.5649, "CAD": 0.94803, "CHF": 0.88117, "CNY": 6.494, "CZK": 16.5798, "DKK": 5.1133, "EUR": 0.68568, "GBP": 0.60429, "HKD": 7.7697, "HRK": 5.0458, "HUF": 180.88, "IDR": 8629, "ILS": 3.404, "INR": 44.368, "JPY": 81.95, "KRW": 1082.24, "LTL": 2.3675, "LVL": 0.48635, "MXN": 11.6127, "MYR": 3.0075, "NOK": 5.3375, "NZD": 1.2479, "PHP": 43.138, "PLN": 2.708, "RON": 2.8022, "RUB": 27.935, "SEK": 6.0947, "SGD": 1.2355, "THB": 29.91, "TRY": 1.5155, "ZAR": 6.746}}