{"file_metadata": {"source": "Frankfurter Exchange Rates API", "fetch_time": "2026-04-07 22:35:41", "base_currency": "USD", "amount": 1.0, "start_date": "2000-01-01", "end_date": "", "file_date": "2020-08-18", "currency_codes": ["AUD", "BGN", "BRL", "CAD", "CHF", "CNY", "CZK", "DKK", "EUR", "GBP", "HKD", "HRK", "HUF", "IDR", "ILS", "INR", "ISK", "JPY", "KRW", "MXN", "MYR", "NOK", "NZD", "PHP", "PLN", "RON", "RUB", "SEK", "SGD", "THB", "TRY", "ZAR"], "count_of_currencies": 32}, "data": {"AUD": 1.3814, "BGN": 1.6427, "BRL": 5.4408, "CAD": 1.3163, "CHF": 0.90484, "CNY": 6.9215, "CZK": 21.95, "DKK": 6.2545, "EUR": 0.83991, "GBP": 0.75907, "HKD": 7.7502, "HRK": 6.3242, "HUF": 293.84, "IDR": 14845, "ILS": 3.4022, "INR": 74.651, "ISK": 135.9, "JPY": 105.44, "KRW": 1184.34, "MXN": 22.059, "MYR": 4.1825, "NOK": 8.8199, "NZD": 1.5218, "PHP": 48.55, "PLN": 3.6847, "RON": 4.0614, "RUB": 73.114, "SEK": 8.6679, "SGD": 1.3649, "THB": 31.12, "TRY": 7.3932, "ZAR": 17.3988}}