{"file_metadata": {"source": "Frankfurter Exchange Rates API", "fetch_time": "2026-04-07 22:35:41", "base_currency": "USD", "amount": 1.0, "start_date": "2000-01-01", "end_date": "", "file_date": "2015-08-10", "currency_codes": ["AUD", "BGN", "BRL", "CAD", "CHF", "CNY", "CZK", "DKK", "EUR", "GBP", "HKD", "HRK", "HUF", "IDR", "ILS", "INR", "JPY", "KRW", "MXN", "MYR", "NOK", "NZD", "PHP", "PLN", "RON", "RUB", "SEK", "SGD", "THB", "TRY", "ZAR"], "count_of_currencies": 31}, "data": {"AUD": 1.358, "BGN": 1.7845, "BRL": 3.5182, "CAD": 1.3131, "CHF": 0.9854, "CNY": 6.2097, "CZK": 24.666, "DKK": 6.8083, "EUR": 0.91241, "GBP": 0.64516, "HKD": 7.7526, "HRK": 6.8714, "HUF": 284.01, "IDR": 13526, "ILS": 3.8097, "INR": 63.871, "JPY": 124.7, "KRW": 1163.4, "MXN": 16.2065, "MYR": 3.9365, "NOK": 8.2354, "NZD": 1.5208, "PHP": 45.815, "PLN": 3.8292, "RON": 4.0254, "RUB": 64.243, "SEK": 8.7553, "SGD": 1.386, "THB": 35.14, "TRY": 2.7911, "ZAR": 12.7258}}