{"file_metadata": {"source": "Frankfurter Exchange Rates API", "fetch_time": "2026-04-07 22:35:41", "base_currency": "USD", "amount": 1.0, "start_date": "2000-01-01", "end_date": "", "file_date": "2005-03-10", "currency_codes": ["AUD", "BGN", "CAD", "CHF", "CYP", "CZK", "DKK", "EEK", "EUR", "GBP", "HKD", "HUF", "ISK", "JPY", "KRW", "LTL", "LVL", "MTL", "NOK", "NZD", "PLN", "ROL", "SEK", "SGD", "SIT", "SKK", "TRY", "ZAR"], "count_of_currencies": 28}, "data": {"AUD": 1.2632, "BGN": 1.4586, "CAD": 1.2016, "CHF": 1.1547, "CYP": 0.43441, "CZK": 22.002, "DKK": 5.5529, "EEK": 11.6687, "EUR": 0.74577, "GBP": 0.51939, "HKD": 7.7992, "HUF": 181.88, "ISK": 59.02, "JPY": 104.12, "KRW": 1000.3, "LTL": 2.575, "LVL": 0.5192, "MTL": 0.32269, "NOK": 6.0959, "NZD": 1.3533, "PLN": 2.9626, "ROL": 26886, "SEK": 6.7636, "SGD": 1.6206, "SIT": 178.76, "SKK": 28.161, "TRY": 1.2838, "ZAR": 5.8855}}