{"file_metadata": {"source": "Frankfurter Exchange Rates API", "fetch_time": "2026-04-07 22:35:41", "base_currency": "USD", "amount": 1.0, "start_date": "2000-01-01", "end_date": "", "file_date": "2022-11-07", "currency_codes": ["AUD", "BGN", "BRL", "CAD", "CHF", "CNY", "CZK", "DKK", "EUR", "GBP", "HKD", "HRK", "HUF", "IDR", "ILS", "INR", "ISK", "JPY", "KRW", "MXN", "MYR", "NOK", "NZD", "PHP", "PLN", "RON", "SEK", "SGD", "THB", "TRY", "ZAR"], "count_of_currencies": 31}, "data": {"AUD": 1.5439, "BGN": 1.9572, "BRL": 5.0736, "CAD": 1.3473, "CHF": 0.98809, "CNY": 7.224, "CZK": 24.318, "DKK": 7.4445, "EUR": 1.0007, "GBP": 0.87196, "HKD": 7.8499, "HRK": 7.5428, "HUF": 401.31, "IDR": 15660, "ILS": 3.5427, "INR": 81.9, "ISK": 146.0, "JPY": 146.28, "KRW": 1392.22, "MXN": 19.4531, "MYR": 4.7395, "NOK": 10.2627, "NZD": 1.6846, "PHP": 58.402, "PLN": 4.6898, "RON": 4.8889, "SEK": 10.8396, "SGD": 1.4032, "THB": 37.31, "TRY": 18.6005, "ZAR": 17.7707}}