{"file_metadata": {"source": "Frankfurter Exchange Rates API", "fetch_time": "2026-04-07 22:35:41", "base_currency": "USD", "amount": 1.0, "start_date": "2000-01-01", "end_date": "", "file_date": "2004-02-06", "currency_codes": ["AUD", "BGN", "CAD", "CHF", "CYP", "CZK", "DKK", "EEK", "EUR", "GBP", "HKD", "HUF", "ISK", "JPY", "KRW", "LTL", "LVL", "MTL", "NOK", "NZD", "PLN", "ROL", "SEK", "SGD", "SIT", "SKK", "TRL", "ZAR"], "count_of_currencies": 28}, "data": {"AUD": 1.3136, "BGN": 1.5609, "CAD": 1.3381, "CHF": 1.2526, "CYP": 0.46791, "CZK": 26.504, "DKK": 5.9466, "EEK": 12.4883, "EUR": 0.79815, "GBP": 0.54526, "HKD": 7.7748, "HUF": 214.26, "ISK": 68.84, "JPY": 106.58, "KRW": 1168.05, "LTL": 2.7563, "LVL": 0.53268, "MTL": 0.34225, "NOK": 6.9722, "NZD": 1.459, "PLN": 3.8808, "ROL": 32647, "SEK": 7.2771, "SGD": 1.6949, "SIT": 189.42, "SKK": 32.485, "TRL": 1349988, "ZAR": 7.0676}}