{"file_metadata": {"source": "Frankfurter Exchange Rates API", "fetch_time": "2026-04-07 22:35:41", "base_currency": "USD", "amount": 1.0, "start_date": "2000-01-01", "end_date": "", "file_date": "2005-09-22", "currency_codes": ["AUD", "BGN", "CAD", "CHF", "CNY", "CYP", "CZK", "DKK", "EEK", "EUR", "GBP", "HKD", "HRK", "HUF", "IDR", "ISK", "JPY", "KRW", "LTL", "LVL", "MTL", "MYR", "NOK", "NZD", "PHP", "PLN", "RON", "RUB", "SEK", "SGD", "SIT", "SKK", "THB", "TRY", "ZAR"], "count_of_currencies": 35}, "data": {"AUD": 1.3015, "BGN": 1.5998, "CAD": 1.1652, "CHF": 1.2708, "CNY": 8.0881, "CYP": 0.46875, "CZK": 24.096, "DKK": 6.1034, "EEK": 12.7999, "EUR": 0.81806, "GBP": 0.55522, "HKD": 7.7599, "HRK": 6.0903, "HUF": 202.34, "IDR": 10225, "ISK": 61.347, "JPY": 111.17, "KRW": 1025.7, "LTL": 2.8246, "LVL": 0.56945, "MTL": 0.35119, "MYR": 3.7696, "NOK": 6.3637, "NZD": 1.4321, "PHP": 56.175, "PLN": 3.199, "RON": 2.9043, "RUB": 28.351, "SEK": 7.6583, "SGD": 1.6797, "SIT": 195.91, "SKK": 31.495, "THB": 41.036, "TRY": 1.3392, "ZAR": 6.3447}}