{"file_metadata": {"source": "Frankfurter Exchange Rates API", "fetch_time": "2026-04-07 22:35:41", "base_currency": "USD", "amount": 1.0, "start_date": "2000-01-01", "end_date": "", "file_date": "2023-11-28", "currency_codes": ["AUD", "BGN", "BRL", "CAD", "CHF", "CNY", "CZK", "DKK", "EUR", "GBP", "HKD", "HUF", "IDR", "ILS", "INR", "ISK", "JPY", "KRW", "MXN", "MYR", "NOK", "NZD", "PHP", "PLN", "RON", "SEK", "SGD", "THB", "TRY", "ZAR"], "count_of_currencies": 30}, "data": {"AUD": 1.5131, "BGN": 1.7863, "BRL": 4.8948, "CAD": 1.3597, "CHF": 0.8809, "CNY": 7.1534, "CZK": 22.253, "DKK": 6.8098, "EUR": 0.91333, "GBP": 0.79295, "HKD": 7.7969, "HUF": 346.93, "IDR": 15486, "ILS": 3.7032, "INR": 83.35, "ISK": 137.82, "JPY": 148.63, "KRW": 1296.82, "MXN": 17.1792, "MYR": 4.6715, "NOK": 10.701, "NZD": 1.6422, "PHP": 55.435, "PLN": 3.9705, "RON": 4.5416, "SEK": 10.442, "SGD": 1.3362, "THB": 34.92, "TRY": 28.933, "ZAR": 18.7076}}