{"file_metadata": {"source": "Frankfurter Exchange Rates API", "fetch_time": "2026-04-07 22:35:41", "base_currency": "USD", "amount": 1.0, "start_date": "2000-01-01", "end_date": "", "file_date": "2001-05-23", "currency_codes": ["AUD", "BGN", "CAD", "CHF", "CYP", "CZK", "DKK", "EEK", "EUR", "GBP", "HKD", "HUF", "ISK", "JPY", "KRW", "LTL", "LVL", "MTL", "NOK", "NZD", "PLN", "ROL", "SEK", "SGD", "SIT", "SKK", "TRL", "ZAR"], "count_of_currencies": 28}, "data": {"AUD": 1.9307, "BGN": 2.2669, "CAD": 1.5456, "CHF": 1.7786, "CYP": 0.67222, "CZK": 39.875, "DKK": 8.6888, "EEK": 18.2255, "EUR": 1.1648, "GBP": 0.7032, "HKD": 7.7999, "HUF": 299.6, "ISK": 101.3, "JPY": 121.15, "KRW": 1286.5, "LTL": 4.0013, "LVL": 0.63273, "MTL": 0.46115, "NOK": 9.2533, "NZD": 2.3672, "PLN": 3.9977, "ROL": 28581, "SEK": 10.5434, "SGD": 1.8052, "SIT": 253.42, "SKK": 50.215, "TRL": 1114735, "ZAR": 7.915}}