{"file_metadata": {"source": "Frankfurter Exchange Rates API", "fetch_time": "2026-04-07 22:35:41", "base_currency": "USD", "amount": 1.0, "start_date": "2000-01-01", "end_date": "", "file_date": "2021-06-11", "currency_codes": ["AUD", "BGN", "BRL", "CAD", "CHF", "CNY", "CZK", "DKK", "EUR", "GBP", "HKD", "HRK", "HUF", "IDR", "ILS", "INR", "ISK", "JPY", "KRW", "MXN", "MYR", "NOK", "NZD", "PHP", "PLN", "RON", "RUB", "SEK", "SGD", "THB", "TRY", "ZAR"], "count_of_currencies": 32}, "data": {"AUD": 1.2938, "BGN": 1.613, "BRL": 5.0788, "CAD": 1.2113, "CHF": 0.89757, "CNY": 6.3933, "CZK": 20.895, "DKK": 6.1329, "EUR": 0.82474, "GBP": 0.70689, "HKD": 7.7599, "HRK": 6.1786, "HUF": 285.56, "IDR": 14199, "ILS": 3.2479, "INR": 73.13, "ISK": 121.4, "JPY": 109.59, "KRW": 1114.3, "MXN": 19.7113, "MYR": 4.108, "NOK": 8.3157, "NZD": 1.3964, "PHP": 47.733, "PLN": 3.6862, "RON": 4.0563, "RUB": 71.72, "SEK": 8.3005, "SGD": 1.3245, "THB": 31.065, "TRY": 8.4098, "ZAR": 13.5903}}