{"file_metadata": {"source": "Frankfurter Exchange Rates API", "fetch_time": "2026-04-07 22:35:41", "base_currency": "USD", "amount": 1.0, "start_date": "2000-01-01", "end_date": "", "file_date": "2007-09-11", "currency_codes": ["AUD", "BGN", "CAD", "CHF", "CNY", "CYP", "CZK", "DKK", "EEK", "EUR", "GBP", "HKD", "HRK", "HUF", "IDR", "ISK", "JPY", "KRW", "LTL", "LVL", "MTL", "MYR", "NOK", "NZD", "PHP", "PLN", "RON", "RUB", "SEK", "SGD", "SKK", "THB", "TRY", "ZAR"], "count_of_currencies": 34}, "data": {"AUD": 1.2091, "BGN": 1.4148, "CAD": 1.0465, "CHF": 1.1864, "CNY": 7.5232, "CYP": 0.4226, "CZK": 19.987, "DKK": 5.3872, "EEK": 11.3184, "EUR": 0.72338, "GBP": 0.49204, "HKD": 7.7843, "HRK": 5.2978, "HUF": 184.16, "IDR": 9440, "ISK": 65.003, "JPY": 113.79, "KRW": 936.4, "LTL": 2.4977, "LVL": 0.50666, "MTL": 0.31055, "MYR": 3.5145, "NOK": 5.6796, "NZD": 1.4337, "PHP": 47.06, "PLN": 2.7412, "RON": 2.3989, "RUB": 25.481, "SEK": 6.7419, "SGD": 1.5226, "SKK": 24.332, "THB": 32.342, "TRY": 1.2869, "ZAR": 7.1683}}