{"file_metadata": {"source": "Frankfurter Exchange Rates API", "fetch_time": "2026-04-07 22:35:41", "base_currency": "USD", "amount": 1.0, "start_date": "2000-01-01", "end_date": "", "file_date": "2009-03-02", "currency_codes": ["AUD", "BGN", "BRL", "CAD", "CHF", "CNY", "CZK", "DKK", "EEK", "EUR", "GBP", "HKD", "HRK", "HUF", "IDR", "INR", "JPY", "KRW", "LTL", "LVL", "MXN", "MYR", "NOK", "NZD", "PHP", "PLN", "RON", "RUB", "SEK", "SGD", "THB", "TRY", "ZAR"], "count_of_currencies": 33}, "data": {"AUD": 1.5774, "BGN": 1.5527, "BRL": 2.4142, "CAD": 1.2884, "CHF": 1.1757, "CNY": 6.8458, "CZK": 22.46, "DKK": 5.9155, "EEK": 12.4219, "EUR": 0.7939, "GBP": 0.70919, "HKD": 7.7565, "HRK": 5.8557, "HUF": 243.75, "IDR": 12080, "INR": 51.885, "JPY": 97.27, "KRW": 1583.0, "LTL": 2.7412, "LVL": 0.56327, "MXN": 15.381, "MYR": 3.728, "NOK": 7.1674, "NZD": 2.0253, "PHP": 49.016, "PLN": 3.771, "RON": 3.416, "RUB": 36.185, "SEK": 9.1898, "SGD": 1.555, "THB": 36.25, "TRY": 1.7269, "ZAR": 10.3735}}