{"file_metadata": {"source": "Frankfurter Exchange Rates API", "fetch_time": "2026-04-07 22:35:41", "base_currency": "USD", "amount": 1.0, "start_date": "2000-01-01", "end_date": "", "file_date": "2013-02-11", "currency_codes": ["AUD", "BGN", "BRL", "CAD", "CHF", "CNY", "CZK", "DKK", "EUR", "GBP", "HKD", "HRK", "HUF", "IDR", "ILS", "INR", "JPY", "KRW", "LTL", "LVL", "MXN", "MYR", "NOK", "NZD", "PHP", "PLN", "RON", "RUB", "SEK", "SGD", "THB", "TRY", "ZAR"], "count_of_currencies": 33}, "data": {"AUD": 0.97297, "BGN": 1.4605, "BRL": 1.9736, "CAD": 1.0077, "CHF": 0.91808, "CNY": 6.2324, "CZK": 18.8485, "DKK": 5.5722, "EUR": 0.74677, "GBP": 0.63737, "HKD": 7.755, "HRK": 5.6579, "HUF": 217.85, "IDR": 9611, "ILS": 3.7019, "INR": 53.855, "JPY": 93.44, "KRW": 1093.88, "LTL": 2.5784, "LVL": 0.52237, "MXN": 12.7675, "MYR": 3.0985, "NOK": 5.5108, "NZD": 1.2009, "PHP": 40.725, "PLN": 3.1019, "RON": 3.286, "RUB": 30.17, "SEK": 6.4039, "SGD": 1.2396, "THB": 29.85, "TRY": 1.7731, "ZAR": 8.9123}}