{"file_metadata": {"source": "Frankfurter Exchange Rates API", "fetch_time": "2026-04-07 22:35:41", "base_currency": "USD", "amount": 1.0, "start_date": "2000-01-01", "end_date": "", "file_date": "2018-08-22", "currency_codes": ["AUD", "BGN", "BRL", "CAD", "CHF", "CNY", "CZK", "DKK", "EUR", "GBP", "HKD", "HRK", "HUF", "IDR", "ILS", "INR", "ISK", "JPY", "KRW", "MXN", "MYR", "NOK", "NZD", "PHP", "PLN", "RON", "RUB", "SEK", "SGD", "THB", "TRY", "ZAR"], "count_of_currencies": 32}, "data": {"AUD": 1.3589, "BGN": 1.6837, "BRL": 4.0386, "CAD": 1.3022, "CHF": 0.98149, "CNY": 6.8414, "CZK": 22.146, "DKK": 6.4211, "EUR": 0.86088, "GBP": 0.77417, "HKD": 7.8499, "HRK": 6.3959, "HUF": 278.01, "IDR": 14580, "ILS": 3.6355, "INR": 69.895, "ISK": 107.44, "JPY": 110.26, "KRW": 1118.24, "MXN": 18.8378, "MYR": 4.1025, "NOK": 8.334, "NZD": 1.491, "PHP": 53.399, "PLN": 3.6864, "RON": 4.0018, "RUB": 67.95, "SEK": 9.0457, "SGD": 1.3654, "THB": 32.73, "TRY": 6.0323, "ZAR": 14.2737}}