{"file_metadata": {"source": "Frankfurter Exchange Rates API", "fetch_time": "2026-04-07 22:35:41", "base_currency": "USD", "amount": 1.0, "start_date": "2000-01-01", "end_date": "", "file_date": "2010-03-23", "currency_codes": ["AUD", "BGN", "BRL", "CAD", "CHF", "CNY", "CZK", "DKK", "EEK", "EUR", "GBP", "HKD", "HRK", "HUF", "IDR", "INR", "JPY", "KRW", "LTL", "LVL", "MXN", "MYR", "NOK", "NZD", "PHP", "PLN", "RON", "RUB", "SEK", "SGD", "THB", "TRY", "ZAR"], "count_of_currencies": 33}, "data": {"AUD": 1.0905, "BGN": 1.4467, "BRL": 1.7813, "CAD": 1.0191, "CHF": 1.0593, "CNY": 6.8263, "CZK": 18.8194, "DKK": 5.5037, "EEK": 11.5738, "EUR": 0.7397, "GBP": 0.6661, "HKD": 7.7622, "HRK": 5.3706, "HUF": 195.73, "IDR": 9120, "INR": 45.555, "JPY": 90.36, "KRW": 1137.03, "LTL": 2.554, "LVL": 0.52378, "MXN": 12.5175, "MYR": 3.3195, "NOK": 5.9487, "NZD": 1.4183, "PHP": 45.589, "PLN": 2.8813, "RON": 3.0124, "RUB": 29.501, "SEK": 7.1962, "SGD": 1.4016, "THB": 32.325, "TRY": 1.5432, "ZAR": 7.3343}}