{"file_metadata": {"source": "Frankfurter Exchange Rates API", "fetch_time": "2026-04-07 22:35:41", "base_currency": "USD", "amount": 1.0, "start_date": "2000-01-01", "end_date": "", "file_date": "2021-04-07", "currency_codes": ["AUD", "BGN", "BRL", "CAD", "CHF", "CNY", "CZK", "DKK", "EUR", "GBP", "HKD", "HRK", "HUF", "IDR", "ILS", "INR", "ISK", "JPY", "KRW", "MXN", "MYR", "NOK", "NZD", "PHP", "PLN", "RON", "RUB", "SEK", "SGD", "THB", "TRY", "ZAR"], "count_of_currencies": 32}, "data": {"AUD": 1.3111, "BGN": 1.6457, "BRL": 5.5907, "CAD": 1.2607, "CHF": 0.92932, "CNY": 6.5433, "CZK": 21.81, "DKK": 6.2576, "EUR": 0.84147, "GBP": 0.72421, "HKD": 7.7858, "HRK": 6.3752, "HUF": 302.66, "IDR": 14562, "ILS": 3.3016, "INR": 74.36, "ISK": 126.56, "JPY": 109.86, "KRW": 1117.51, "MXN": 20.203, "MYR": 4.1315, "NOK": 8.4597, "NZD": 1.4227, "PHP": 48.776, "PLN": 3.8502, "RON": 4.1388, "RUB": 77.701, "SEK": 8.6133, "SGD": 1.3394, "THB": 31.375, "TRY": 8.1813, "ZAR": 14.5408}}