{"file_metadata": {"source": "Frankfurter Exchange Rates API", "fetch_time": "2026-04-07 22:35:41", "base_currency": "USD", "amount": 1.0, "start_date": "2000-01-01", "end_date": "", "file_date": "2005-05-31", "currency_codes": ["AUD", "BGN", "CAD", "CHF", "CNY", "CYP", "CZK", "DKK", "EEK", "EUR", "GBP", "HKD", "HRK", "HUF", "IDR", "ISK", "JPY", "KRW", "LTL", "LVL", "MTL", "MYR", "NOK", "NZD", "PHP", "PLN", "ROL", "RUB", "SEK", "SGD", "SIT", "SKK", "THB", "TRY", "ZAR"], "count_of_currencies": 35}, "data": {"AUD": 1.3226, "BGN": 1.5858, "CAD": 1.2595, "CHF": 1.2466, "CNY": 8.2765, "CYP": 0.46712, "CZK": 24.631, "DKK": 6.0354, "EEK": 12.6888, "EUR": 0.81096, "GBP": 0.5491, "HKD": 7.7793, "HRK": 5.9419, "HUF": 205.66, "IDR": 9508, "ISK": 64.723, "JPY": 108.24, "KRW": 1007.95, "LTL": 2.8001, "LVL": 0.56443, "MTL": 0.34815, "MYR": 3.8, "NOK": 6.4382, "NZD": 1.4155, "PHP": 54.52, "PLN": 3.3379, "ROL": 29369, "RUB": 28.252, "SEK": 7.4291, "SGD": 1.6667, "SIT": 194.21, "SKK": 31.68, "THB": 40.595, "TRY": 1.3582, "ZAR": 6.7188}}