{"file_metadata": {"source": "Frankfurter Exchange Rates API", "fetch_time": "2026-04-07 22:35:41", "base_currency": "USD", "amount": 1.0, "start_date": "2000-01-01", "end_date": "", "file_date": "2023-07-17", "currency_codes": ["AUD", "BGN", "BRL", "CAD", "CHF", "CNY", "CZK", "DKK", "EUR", "GBP", "HKD", "HUF", "IDR", "ILS", "INR", "ISK", "JPY", "KRW", "MXN", "MYR", "NOK", "NZD", "PHP", "PLN", "RON", "SEK", "SGD", "THB", "TRY", "ZAR"], "count_of_currencies": 30}, "data": {"AUD": 1.4681, "BGN": 1.7416, "BRL": 4.805, "CAD": 1.3219, "CHF": 0.85948, "CNY": 7.1645, "CZK": 21.155, "DKK": 6.6344, "EUR": 0.89047, "GBP": 0.76467, "HKD": 7.8139, "HUF": 332.17, "IDR": 14998, "ILS": 3.6418, "INR": 82.02, "ISK": 130.81, "JPY": 138.36, "KRW": 1266.18, "MXN": 16.7833, "MYR": 4.5405, "NOK": 10.0107, "NZD": 1.5785, "PHP": 54.43, "PLN": 3.9633, "RON": 4.4002, "SEK": 10.2291, "SGD": 1.3214, "THB": 34.6, "TRY": 26.315, "ZAR": 18.0392}}