{"file_metadata": {"source": "Frankfurter Exchange Rates API", "fetch_time": "2026-04-07 22:35:41", "base_currency": "USD", "amount": 1.0, "start_date": "2000-01-01", "end_date": "", "file_date": "2003-01-09", "currency_codes": ["AUD", "BGN", "CAD", "CHF", "CYP", "CZK", "DKK", "EEK", "EUR", "GBP", "HKD", "HUF", "ISK", "JPY", "KRW", "LTL", "LVL", "MTL", "NOK", "NZD", "PLN", "ROL", "SEK", "SGD", "SIT", "SKK", "TRL", "ZAR"], "count_of_currencies": 28}, "data": {"AUD": 1.7295, "BGN": 1.8614, "CAD": 1.5581, "CHF": 1.3893, "CYP": 0.5471, "CZK": 30.026, "DKK": 7.0712, "EEK": 14.8916, "EUR": 0.95175, "GBP": 0.62149, "HKD": 7.7992, "HUF": 223.77, "ISK": 80.82, "JPY": 119.12, "KRW": 1178.5, "LTL": 3.2867, "LVL": 0.58704, "MTL": 0.3984, "NOK": 6.8768, "NZD": 1.8735, "PLN": 3.8277, "ROL": 33678, "SEK": 8.6714, "SGD": 1.7364, "SIT": 219.42, "SKK": 39.488, "TRL": 1676977, "ZAR": 8.5525}}