{"file_metadata": {"source": "Frankfurter Exchange Rates API", "fetch_time": "2026-04-07 22:35:41", "base_currency": "USD", "amount": 1.0, "start_date": "2000-01-01", "end_date": "", "file_date": "2019-09-24", "currency_codes": ["AUD", "BGN", "BRL", "CAD", "CHF", "CNY", "CZK", "DKK", "EUR", "GBP", "HKD", "HRK", "HUF", "IDR", "ILS", "INR", "ISK", "JPY", "KRW", "MXN", "MYR", "NOK", "NZD", "PHP", "PLN", "RON", "RUB", "SEK", "SGD", "THB", "TRY", "ZAR"], "count_of_currencies": 32}, "data": {"AUD": 1.4713, "BGN": 1.7775, "BRL": 4.1588, "CAD": 1.3256, "CHF": 0.98864, "CNY": 7.1071, "CZK": 23.514, "DKK": 6.7855, "EUR": 0.90884, "GBP": 0.80117, "HKD": 7.8401, "HRK": 6.7291, "HUF": 304.62, "IDR": 14113, "ILS": 3.504, "INR": 70.948, "ISK": 124.69, "JPY": 107.65, "KRW": 1193.91, "MXN": 19.4402, "MYR": 4.1815, "NOK": 9.018, "NZD": 1.5839, "PHP": 52.129, "PLN": 3.9819, "RON": 4.3156, "RUB": 63.643, "SEK": 9.7031, "SGD": 1.3764, "THB": 30.564, "TRY": 5.6851, "ZAR": 14.8686}}