{"file_metadata": {"source": "Frankfurter Exchange Rates API", "fetch_time": "2026-04-07 22:35:41", "base_currency": "USD", "amount": 1.0, "start_date": "2000-01-01", "end_date": "", "file_date": "2000-03-22", "currency_codes": ["AUD", "CAD", "CHF", "CYP", "CZK", "DKK", "EEK", "EUR", "GBP", "HKD", "HUF", "ISK", "JPY", "KRW", "LTL", "LVL", "MTL", "NOK", "NZD", "PLN", "ROL", "SEK", "SGD", "SIT", "SKK", "TRL", "ZAR"], "count_of_currencies": 27}, "data": {"AUD": 1.6471, "CAD": 1.4689, "CHF": 1.676, "CYP": 0.59878, "CZK": 37.032, "DKK": 7.7548, "EEK": 16.2934, "EUR": 1.0413, "GBP": 0.63782, "HKD": 7.7828, "HUF": 267.47, "ISK": 74.143, "JPY": 107.13, "KRW": 1112.52, "LTL": 4.0004, "LVL": 0.59513, "MTL": 0.4258, "NOK": 8.4843, "NZD": 2.0514, "PLN": 4.0615, "ROL": 19318, "SEK": 8.7098, "SGD": 1.7156, "SIT": 211.32, "SKK": 43.414, "TRL": 583398, "ZAR": 6.455}}