{"file_metadata": {"source": "Frankfurter Exchange Rates API", "fetch_time": "2026-04-07 22:35:41", "base_currency": "USD", "amount": 1.0, "start_date": "2000-01-01", "end_date": "", "file_date": "2011-01-06", "currency_codes": ["AUD", "BGN", "BRL", "CAD", "CHF", "CNY", "CZK", "DKK", "EUR", "GBP", "HKD", "HRK", "HUF", "IDR", "ILS", "INR", "JPY", "KRW", "LTL", "LVL", "MXN", "MYR", "NOK", "NZD", "PHP", "PLN", "RON", "RUB", "SEK", "SGD", "THB", "TRY", "ZAR"], "count_of_currencies": 33}, "data": {"AUD": 1.0036, "BGN": 1.494, "BRL": 1.6838, "CAD": 0.99389, "CHF": 0.96838, "CNY": 6.6265, "CZK": 18.8756, "DKK": 5.6922, "EUR": 0.76388, "GBP": 0.6451, "HKD": 7.7746, "HRK": 5.6524, "HUF": 210.79, "IDR": 8997, "ILS": 3.5624, "INR": 45.285, "JPY": 83.2, "KRW": 1119.96, "LTL": 2.6375, "LVL": 0.53586, "MXN": 12.18, "MYR": 3.0685, "NOK": 5.9182, "NZD": 1.3192, "PHP": 43.92, "PLN": 2.945, "RON": 3.2522, "RUB": 30.581, "SEK": 6.8146, "SGD": 1.2939, "THB": 30.225, "TRY": 1.5469, "ZAR": 6.7672}}