{"file_metadata": {"source": "Frankfurter Exchange Rates API", "fetch_time": "2026-04-07 22:35:41", "base_currency": "USD", "amount": 1.0, "start_date": "2000-01-01", "end_date": "", "file_date": "2002-07-30", "currency_codes": ["AUD", "BGN", "CAD", "CHF", "CYP", "CZK", "DKK", "EEK", "EUR", "GBP", "HKD", "HUF", "ISK", "JPY", "KRW", "LTL", "LVL", "MTL", "NOK", "NZD", "PLN", "ROL", "SEK", "SGD", "SIT", "SKK", "TRL", "ZAR"], "count_of_currencies": 28}, "data": {"AUD": 1.8358, "BGN": 1.9791, "CAD": 1.5715, "CHF": 1.4824, "CYP": 0.58469, "CZK": 30.75, "DKK": 7.5562, "EEK": 15.9091, "EUR": 1.0168, "GBP": 0.63996, "HKD": 7.7999, "HUF": 248.5, "ISK": 85.48, "JPY": 119.61, "KRW": 1183.1, "LTL": 3.5101, "LVL": 0.60203, "MTL": 0.42074, "NOK": 7.6309, "NZD": 2.1213, "PLN": 4.1487, "ROL": 32877, "SEK": 9.3782, "SGD": 1.7632, "SIT": 230.78, "SKK": 45.135, "TRL": 1689883, "ZAR": 10.1755}}