{"file_metadata": {"source": "Frankfurter Exchange Rates API", "fetch_time": "2026-04-07 22:35:41", "base_currency": "USD", "amount": 1.0, "start_date": "2000-01-01", "end_date": "", "file_date": "2003-11-20", "currency_codes": ["AUD", "BGN", "CAD", "CHF", "CYP", "CZK", "DKK", "EEK", "EUR", "GBP", "HKD", "HUF", "ISK", "JPY", "KRW", "LTL", "LVL", "MTL", "NOK", "NZD", "PLN", "ROL", "SEK", "SGD", "SIT", "SKK", "TRL", "ZAR"], "count_of_currencies": 28}, "data": {"AUD": 1.3824, "BGN": 1.6361, "CAD": 1.303, "CHF": 1.2999, "CYP": 0.49017, "CZK": 26.748, "DKK": 6.2453, "EEK": 13.1385, "EUR": 0.8397, "GBP": 0.58729, "HKD": 7.7603, "HUF": 216.74, "ISK": 74.775, "JPY": 108.88, "KRW": 1191.7, "LTL": 2.8994, "LVL": 0.54824, "MTL": 0.36023, "NOK": 6.8629, "NZD": 1.5548, "PLN": 3.8954, "ROL": 33726, "SEK": 7.5355, "SGD": 1.7174, "SIT": 198.32, "SKK": 34.386, "TRL": 1482499, "ZAR": 6.5938}}