{"file_metadata": {"source": "Frankfurter Exchange Rates API", "fetch_time": "2026-04-07 22:35:41", "base_currency": "USD", "amount": 1.0, "start_date": "2000-01-01", "end_date": "", "file_date": "2011-06-20", "currency_codes": ["AUD", "BGN", "BRL", "CAD", "CHF", "CNY", "CZK", "DKK", "EUR", "GBP", "HKD", "HRK", "HUF", "IDR", "ILS", "INR", "JPY", "KRW", "LTL", "LVL", "MXN", "MYR", "NOK", "NZD", "PHP", "PLN", "RON", "RUB", "SEK", "SGD", "THB", "TRY", "ZAR"], "count_of_currencies": 33}, "data": {"AUD": 0.95033, "BGN": 1.3739, "BRL": 1.6065, "CAD": 0.98377, "CHF": 0.84573, "CNY": 6.4781, "CZK": 16.9477, "DKK": 5.2402, "EUR": 0.70249, "GBP": 0.61784, "HKD": 7.7939, "HRK": 5.1879, "HUF": 188.97, "IDR": 8617, "ILS": 3.4586, "INR": 45.007, "JPY": 80.25, "KRW": 1085.91, "LTL": 2.4256, "LVL": 0.49807, "MXN": 11.9361, "MYR": 3.0395, "NOK": 5.5683, "NZD": 1.2407, "PHP": 43.69, "PLN": 2.8028, "RON": 3.0004, "RUB": 28.171, "SEK": 6.4424, "SGD": 1.2376, "THB": 30.6, "TRY": 1.6115, "ZAR": 6.7881}}