{"file_metadata": {"source": "Frankfurter Exchange Rates API", "fetch_time": "2026-04-07 22:35:41", "base_currency": "USD", "amount": 1.0, "start_date": "2000-01-01", "end_date": "", "file_date": "2002-04-29", "currency_codes": ["AUD", "BGN", "CAD", "CHF", "CYP", "CZK", "DKK", "EEK", "EUR", "GBP", "HKD", "HUF", "ISK", "JPY", "KRW", "LTL", "LVL", "MTL", "NOK", "NZD", "PLN", "ROL", "SEK", "SGD", "SIT", "SKK", "TRL", "ZAR"], "count_of_currencies": 28}, "data": {"AUD": 1.8465, "BGN": 2.1587, "CAD": 1.5634, "CHF": 1.6195, "CYP": 0.63938, "CZK": 33.772, "DKK": 8.2247, "EEK": 17.312, "EUR": 1.1064, "GBP": 0.68444, "HKD": 7.7992, "HUF": 268.37, "ISK": 93.74, "JPY": 128.0, "KRW": 1288.0, "LTL": 3.8201, "LVL": 0.62658, "MTL": 0.44645, "NOK": 8.3807, "NZD": 2.2264, "PLN": 3.9743, "ROL": 33396, "SEK": 10.2235, "SGD": 1.8078, "SIT": 248.94, "SKK": 46.664, "TRL": 1333260, "ZAR": 10.6012}}