{"file_metadata": {"source": "Frankfurter Exchange Rates API", "fetch_time": "2026-04-07 22:35:41", "base_currency": "USD", "amount": 1.0, "start_date": "2000-01-01", "end_date": "", "file_date": "2000-10-17", "currency_codes": ["AUD", "BGN", "CAD", "CHF", "CYP", "CZK", "DKK", "EEK", "EUR", "GBP", "HKD", "HUF", "ISK", "JPY", "KRW", "LTL", "LVL", "MTL", "NOK", "NZD", "PLN", "ROL", "SEK", "SGD", "SIT", "SKK", "TRL", "ZAR"], "count_of_currencies": 28}, "data": {"AUD": 1.9253, "BGN": 2.2908, "CAD": 1.521, "CHF": 1.78, "CYP": 0.67374, "CZK": 41.616, "DKK": 8.7624, "EEK": 18.4164, "EUR": 1.177, "GBP": 0.69539, "HKD": 7.7979, "HUF": 309.24, "ISK": 85.38, "JPY": 107.97, "KRW": 1133.0, "LTL": 4.0006, "LVL": 0.62288, "MTL": 0.46245, "NOK": 9.4603, "NZD": 2.5406, "PLN": 4.6728, "ROL": 24533, "SEK": 10.01, "SGD": 1.7547, "SIT": 247.45, "SKK": 51.306, "TRL": 678987, "ZAR": 7.539}}