{"file_metadata": {"source": "Frankfurter Exchange Rates API", "fetch_time": "2026-04-07 22:35:41", "base_currency": "USD", "amount": 1.0, "start_date": "2000-01-01", "end_date": "", "file_date": "2021-09-29", "currency_codes": ["AUD", "BGN", "BRL", "CAD", "CHF", "CNY", "CZK", "DKK", "EUR", "GBP", "HKD", "HRK", "HUF", "IDR", "ILS", "INR", "ISK", "JPY", "KRW", "MXN", "MYR", "NOK", "NZD", "PHP", "PLN", "RON", "RUB", "SEK", "SGD", "THB", "TRY", "ZAR"], "count_of_currencies": 32}, "data": {"AUD": 1.3825, "BGN": 1.6782, "BRL": 5.4246, "CAD": 1.2693, "CHF": 0.92921, "CNY": 6.4653, "CZK": 21.844, "DKK": 6.3806, "EUR": 0.85807, "GBP": 0.74175, "HKD": 7.7839, "HRK": 6.4334, "HUF": 308.56, "IDR": 14305, "ILS": 3.2113, "INR": 74.198, "ISK": 129.31, "JPY": 111.46, "KRW": 1185.17, "MXN": 20.343, "MYR": 4.1847, "NOK": 8.7034, "NZD": 1.4438, "PHP": 50.801, "PLN": 3.9695, "RON": 4.244, "RUB": 72.662, "SEK": 8.7378, "SGD": 1.3576, "THB": 33.885, "TRY": 8.8526, "ZAR": 15.0343}}