{"file_metadata": {"source": "Frankfurter Exchange Rates API", "fetch_time": "2026-04-07 22:35:41", "base_currency": "USD", "amount": 1.0, "start_date": "2000-01-01", "end_date": "", "file_date": "2015-01-19", "currency_codes": ["AUD", "BGN", "BRL", "CAD", "CHF", "CNY", "CZK", "DKK", "EUR", "GBP", "HKD", "HRK", "HUF", "IDR", "ILS", "INR", "JPY", "KRW", "MXN", "MYR", "NOK", "NZD", "PHP", "PLN", "RON", "RUB", "SEK", "SGD", "THB", "TRY", "ZAR"], "count_of_currencies": 31}, "data": {"AUD": 1.2179, "BGN": 1.6853, "BRL": 2.6284, "CAD": 1.1983, "CHF": 0.87204, "CNY": 6.2204, "CZK": 24.025, "DKK": 6.4063, "EUR": 0.8617, "GBP": 0.6604, "HKD": 7.7521, "HRK": 6.6295, "HUF": 274.64, "IDR": 12618, "ILS": 3.9297, "INR": 61.712, "JPY": 117.42, "KRW": 1078.01, "MXN": 14.6135, "MYR": 3.5715, "NOK": 7.6109, "NZD": 1.2851, "PHP": 44.57, "PLN": 3.7194, "RON": 3.88, "RUB": 64.652, "SEK": 8.1065, "SGD": 1.3316, "THB": 32.59, "TRY": 2.3394, "ZAR": 11.6513}}