{"file_metadata": {"source": "Frankfurter Exchange Rates API", "fetch_time": "2026-04-07 22:35:41", "base_currency": "USD", "amount": 1.0, "start_date": "2000-01-01", "end_date": "", "file_date": "2022-05-04", "currency_codes": ["AUD", "BGN", "BRL", "CAD", "CHF", "CNY", "CZK", "DKK", "EUR", "GBP", "HKD", "HRK", "HUF", "IDR", "ILS", "INR", "ISK", "JPY", "KRW", "MXN", "MYR", "NOK", "NZD", "PHP", "PLN", "RON", "SEK", "SGD", "THB", "TRY", "ZAR"], "count_of_currencies": 31}, "data": {"AUD": 1.4035, "BGN": 1.8572, "BRL": 4.9758, "CAD": 1.2817, "CHF": 0.98034, "CNY": 6.6085, "CZK": 23.401, "DKK": 7.0657, "EUR": 0.94958, "GBP": 0.79949, "HKD": 7.8487, "HRK": 7.1692, "HUF": 358.51, "IDR": 14435, "ILS": 3.3698, "INR": 76.346, "ISK": 130.28, "JPY": 129.94, "KRW": 1264.31, "MXN": 20.221, "MYR": 4.3535, "NOK": 9.4048, "NZD": 1.5509, "PHP": 52.474, "PLN": 4.4511, "RON": 4.6976, "SEK": 9.8726, "SGD": 1.3825, "THB": 34.315, "TRY": 14.7915, "ZAR": 15.8094}}