{"file_metadata": {"source": "Frankfurter Exchange Rates API", "fetch_time": "2026-04-07 22:35:41", "base_currency": "USD", "amount": 1.0, "start_date": "2000-01-01", "end_date": "", "file_date": "2025-08-13", "currency_codes": ["AUD", "BGN", "BRL", "CAD", "CHF", "CNY", "CZK", "DKK", "EUR", "GBP", "HKD", "HUF", "IDR", "ILS", "INR", "ISK", "JPY", "KRW", "MXN", "MYR", "NOK", "NZD", "PHP", "PLN", "RON", "SEK", "SGD", "THB", "TRY", "ZAR"], "count_of_currencies": 30}, "data": {"AUD": 1.5261, "BGN": 1.6701, "BRL": 5.3905, "CAD": 1.376, "CHF": 0.80343, "CNY": 7.1745, "CZK": 20.896, "DKK": 6.3723, "EUR": 0.8539, "GBP": 0.737, "HKD": 7.85, "HUF": 337.84, "IDR": 16128, "ILS": 3.3899, "INR": 87.45, "ISK": 122.28, "JPY": 147.27, "KRW": 1378.36, "MXN": 18.5407, "MYR": 4.2075, "NOK": 10.199, "NZD": 1.671, "PHP": 56.648, "PLN": 3.6376, "RON": 4.3234, "SEK": 9.5274, "SGD": 1.28, "THB": 32.29, "TRY": 40.745, "ZAR": 17.516}}