{"file_metadata": {"source": "Frankfurter Exchange Rates API", "fetch_time": "2026-04-07 22:35:41", "base_currency": "USD", "amount": 1.0, "start_date": "2000-01-01", "end_date": "", "file_date": "2012-05-10", "currency_codes": ["AUD", "BGN", "BRL", "CAD", "CHF", "CNY", "CZK", "DKK", "EUR", "GBP", "HKD", "HRK", "HUF", "IDR", "ILS", "INR", "JPY", "KRW", "LTL", "LVL", "MXN", "MYR", "NOK", "NZD", "PHP", "PLN", "RON", "RUB", "SEK", "SGD", "THB", "TRY", "ZAR"], "count_of_currencies": 33}, "data": {"AUD": 0.98766, "BGN": 1.509, "BRL": 1.964, "CAD": 0.99877, "CHF": 0.92686, "CNY": 6.3143, "CZK": 19.4136, "DKK": 5.7353, "EUR": 0.77155, "GBP": 0.61863, "HKD": 7.7629, "HRK": 5.7908, "HUF": 222.44, "IDR": 9223, "ILS": 3.8176, "INR": 53.338, "JPY": 79.708, "KRW": 1142.1, "LTL": 2.664, "LVL": 0.53869, "MXN": 13.425, "MYR": 3.0675, "NOK": 5.831, "NZD": 1.268, "PHP": 42.465, "PLN": 3.263, "RON": 3.4095, "RUB": 30.119, "SEK": 6.9013, "SGD": 1.2498, "THB": 31.12, "TRY": 1.785, "ZAR": 8.0086}}