{"file_metadata": {"source": "Frankfurter Exchange Rates API", "fetch_time": "2026-04-07 22:35:41", "base_currency": "USD", "amount": 1.0, "start_date": "2000-01-01", "end_date": "", "file_date": "2018-07-09", "currency_codes": ["AUD", "BGN", "BRL", "CAD", "CHF", "CNY", "CZK", "DKK", "EUR", "GBP", "HKD", "HRK", "HUF", "IDR", "ILS", "INR", "ISK", "JPY", "KRW", "MXN", "MYR", "NOK", "NZD", "PHP", "PLN", "RON", "RUB", "SEK", "SGD", "THB", "TRY", "ZAR"], "count_of_currencies": 32}, "data": {"AUD": 1.3364, "BGN": 1.659, "BRL": 3.865, "CAD": 1.3076, "CHF": 0.98787, "CNY": 6.6135, "CZK": 21.934, "DKK": 6.3223, "EUR": 0.84825, "GBP": 0.74939, "HKD": 7.8485, "HRK": 6.2866, "HUF": 273.76, "IDR": 14325, "ILS": 3.6183, "INR": 68.674, "ISK": 106.2, "JPY": 110.45, "KRW": 1111.1, "MXN": 19.0313, "MYR": 4.0295, "NOK": 7.992, "NZD": 1.4588, "PHP": 53.346, "PLN": 3.6648, "RON": 3.9516, "RUB": 62.677, "SEK": 8.6986, "SGD": 1.3529, "THB": 33.1, "TRY": 4.5179, "ZAR": 13.3103}}