{"file_metadata": {"source": "Frankfurter Exchange Rates API", "fetch_time": "2026-04-07 22:35:41", "base_currency": "USD", "amount": 1.0, "start_date": "2000-01-01", "end_date": "", "file_date": "2013-03-13", "currency_codes": ["AUD", "BGN", "BRL", "CAD", "CHF", "CNY", "CZK", "DKK", "EUR", "GBP", "HKD", "HRK", "HUF", "IDR", "ILS", "INR", "JPY", "KRW", "LTL", "LVL", "MXN", "MYR", "NOK", "NZD", "PHP", "PLN", "RON", "RUB", "SEK", "SGD", "THB", "TRY", "ZAR"], "count_of_currencies": 33}, "data": {"AUD": 0.96857, "BGN": 1.5067, "BRL": 1.9598, "CAD": 1.0249, "CHF": 0.949, "CNY": 6.2142, "CZK": 19.7458, "DKK": 5.7445, "EUR": 0.77036, "GBP": 0.66852, "HKD": 7.7571, "HRK": 5.8443, "HUF": 235.46, "IDR": 9691, "ILS": 3.6916, "INR": 54.306, "JPY": 95.98, "KRW": 1104.52, "LTL": 2.6599, "LVL": 0.54017, "MXN": 12.39, "MYR": 3.108, "NOK": 5.7338, "NZD": 1.2118, "PHP": 40.542, "PLN": 3.1881, "RON": 3.3811, "RUB": 30.753, "SEK": 6.3886, "SGD": 1.2481, "THB": 29.6, "TRY": 1.8111, "ZAR": 9.2131}}