{"file_metadata": {"source": "Frankfurter Exchange Rates API", "fetch_time": "2026-04-07 22:35:41", "base_currency": "USD", "amount": 1.0, "start_date": "2000-01-01", "end_date": "", "file_date": "2019-11-08", "currency_codes": ["AUD", "BGN", "BRL", "CAD", "CHF", "CNY", "CZK", "DKK", "EUR", "GBP", "HKD", "HRK", "HUF", "IDR", "ILS", "INR", "ISK", "JPY", "KRW", "MXN", "MYR", "NOK", "NZD", "PHP", "PLN", "RON", "RUB", "SEK", "SGD", "THB", "TRY", "ZAR"], "count_of_currencies": 32}, "data": {"AUD": 1.456, "BGN": 1.7725, "BRL": 4.1311, "CAD": 1.3196, "CHF": 0.9961, "CNY": 6.9889, "CZK": 23.098, "DKK": 6.7724, "EUR": 0.90629, "GBP": 0.78084, "HKD": 7.8278, "HRK": 6.7378, "HUF": 302.13, "IDR": 14014, "ILS": 3.4922, "INR": 71.281, "ISK": 124.8, "JPY": 109.41, "KRW": 1157.02, "MXN": 19.1572, "MYR": 4.1335, "NOK": 9.1438, "NZD": 1.5793, "PHP": 50.579, "PLN": 3.8617, "RON": 4.3174, "RUB": 63.862, "SEK": 9.6996, "SGD": 1.3596, "THB": 30.385, "TRY": 5.7561, "ZAR": 14.7835}}