{"file_metadata": {"source": "Frankfurter Exchange Rates API", "fetch_time": "2026-04-07 22:35:41", "base_currency": "USD", "amount": 1.0, "start_date": "2000-01-01", "end_date": "", "file_date": "2009-11-17", "currency_codes": ["AUD", "BGN", "BRL", "CAD", "CHF", "CNY", "CZK", "DKK", "EEK", "EUR", "GBP", "HKD", "HRK", "HUF", "IDR", "INR", "JPY", "KRW", "LTL", "LVL", "MXN", "MYR", "NOK", "NZD", "PHP", "PLN", "RON", "RUB", "SEK", "SGD", "THB", "TRY", "ZAR"], "count_of_currencies": 33}, "data": {"AUD": 1.0772, "BGN": 1.3148, "BRL": 1.7135, "CAD": 1.0578, "CHF": 1.0159, "CNY": 6.8265, "CZK": 17.1395, "DKK": 5.0023, "EEK": 10.5187, "EUR": 0.67227, "GBP": 0.5958, "HKD": 7.7501, "HRK": 4.921, "HUF": 178.82, "IDR": 9403, "INR": 46.335, "JPY": 89.25, "KRW": 1155.48, "LTL": 2.3212, "LVL": 0.47624, "MXN": 13.014, "MYR": 3.3675, "NOK": 5.6118, "NZD": 1.3405, "PHP": 46.703, "PLN": 2.7571, "RON": 2.8871, "RUB": 28.773, "SEK": 6.8719, "SGD": 1.387, "THB": 33.2, "TRY": 1.4824, "ZAR": 7.4602}}