{"file_metadata": {"source": "Frankfurter Exchange Rates API", "fetch_time": "2026-04-07 22:35:41", "base_currency": "USD", "amount": 1.0, "start_date": "2000-01-01", "end_date": "", "file_date": "2014-04-04", "currency_codes": ["AUD", "BGN", "BRL", "CAD", "CHF", "CNY", "CZK", "DKK", "EUR", "GBP", "HKD", "HRK", "HUF", "IDR", "ILS", "INR", "JPY", "KRW", "LTL", "MXN", "MYR", "NOK", "NZD", "PHP", "PLN", "RON", "RUB", "SEK", "SGD", "THB", "TRY", "ZAR"], "count_of_currencies": 32}, "data": {"AUD": 1.081, "BGN": 1.4276, "BRL": 2.2682, "CAD": 1.1022, "CHF": 0.89307, "CNY": 6.2123, "CZK": 20.021, "DKK": 5.4491, "EUR": 0.72993, "GBP": 0.60343, "HKD": 7.7577, "HRK": 5.5755, "HUF": 223.85, "IDR": 11322, "ILS": 3.485, "INR": 60.197, "JPY": 103.89, "KRW": 1054.39, "LTL": 2.5203, "MXN": 13.1085, "MYR": 3.2802, "NOK": 5.9945, "NZD": 1.1697, "PHP": 44.948, "PLN": 3.0401, "RON": 3.2525, "RUB": 35.376, "SEK": 6.54, "SGD": 1.2647, "THB": 32.553, "TRY": 2.138, "ZAR": 10.6222}}