{"file_metadata": {"source": "Frankfurter Exchange Rates API", "fetch_time": "2026-04-07 22:35:41", "base_currency": "USD", "amount": 1.0, "start_date": "2000-01-01", "end_date": "", "file_date": "2009-05-20", "currency_codes": ["AUD", "BGN", "BRL", "CAD", "CHF", "CNY", "CZK", "DKK", "EEK", "EUR", "GBP", "HKD", "HRK", "HUF", "IDR", "INR", "JPY", "KRW", "LTL", "LVL", "MXN", "MYR", "NOK", "NZD", "PHP", "PLN", "RON", "RUB", "SEK", "SGD", "THB", "TRY", "ZAR"], "count_of_currencies": 33}, "data": {"AUD": 1.2896, "BGN": 1.4286, "BRL": 2.0321, "CAD": 1.1486, "CHF": 1.1047, "CNY": 6.825, "CZK": 19.4412, "DKK": 5.4384, "EEK": 11.4292, "EUR": 0.73046, "GBP": 0.6447, "HKD": 7.7527, "HRK": 5.3787, "HUF": 202.96, "IDR": 10294, "INR": 47.42, "JPY": 95.73, "KRW": 1246.76, "LTL": 2.5221, "LVL": 0.5179, "MXN": 12.925, "MYR": 3.5375, "NOK": 6.4354, "NZD": 1.6515, "PHP": 47.18, "PLN": 3.1912, "RON": 3.04, "RUB": 31.652, "SEK": 7.6636, "SGD": 1.4605, "THB": 34.455, "TRY": 1.5337, "ZAR": 8.408}}