{"file_metadata": {"source": "Frankfurter Exchange Rates API", "fetch_time": "2026-04-07 22:35:41", "base_currency": "USD", "amount": 1.0, "start_date": "2000-01-01", "end_date": "", "file_date": "2005-04-26", "currency_codes": ["AUD", "BGN", "CAD", "CHF", "CNY", "CYP", "CZK", "DKK", "EEK", "EUR", "GBP", "HKD", "HRK", "HUF", "IDR", "ISK", "JPY", "KRW", "LTL", "LVL", "MTL", "MYR", "NOK", "NZD", "PHP", "PLN", "ROL", "RUB", "SEK", "SGD", "SIT", "SKK", "THB", "TRY", "ZAR"], "count_of_currencies": 35}, "data": {"AUD": 1.2835, "BGN": 1.5067, "CAD": 1.2412, "CHF": 1.1877, "CNY": 8.2765, "CYP": 0.44842, "CZK": 23.301, "DKK": 5.7383, "EEK": 12.0535, "EUR": 0.77036, "GBP": 0.52473, "HKD": 7.7987, "HRK": 5.6891, "HUF": 192.0, "IDR": 9685, "ISK": 63.524, "JPY": 105.95, "KRW": 998.8, "LTL": 2.6599, "LVL": 0.53632, "MTL": 0.3311, "MYR": 3.7999, "NOK": 6.2642, "NZD": 1.3736, "PHP": 54.325, "PLN": 3.2397, "ROL": 27874, "RUB": 27.76, "SEK": 7.0451, "SGD": 1.6473, "SIT": 184.59, "SKK": 30.579, "THB": 39.486, "TRY": 1.3606, "ZAR": 6.095}}