{"file_metadata": {"source": "Frankfurter Exchange Rates API", "fetch_time": "2026-04-07 22:35:41", "base_currency": "USD", "amount": 1.0, "start_date": "2000-01-01", "end_date": "", "file_date": "2005-04-21", "currency_codes": ["AUD", "BGN", "CAD", "CHF", "CNY", "CYP", "CZK", "DKK", "EEK", "EUR", "GBP", "HKD", "HRK", "HUF", "IDR", "ISK", "JPY", "KRW", "LTL", "LVL", "MTL", "MYR", "NOK", "NZD", "PHP", "PLN", "ROL", "RUB", "SEK", "SGD", "SIT", "SKK", "THB", "TRY", "ZAR"], "count_of_currencies": 35}, "data": {"AUD": 1.2921, "BGN": 1.4979, "CAD": 1.2426, "CHF": 1.1814, "CNY": 8.2765, "CYP": 0.44586, "CZK": 23.125, "DKK": 5.7049, "EEK": 11.9824, "EUR": 0.76581, "GBP": 0.52439, "HKD": 7.7994, "HRK": 5.6517, "HUF": 190.08, "IDR": 9675, "ISK": 62.605, "JPY": 107.42, "KRW": 1006.3, "LTL": 2.6442, "LVL": 0.53308, "MTL": 0.32961, "MYR": 3.7999, "NOK": 6.246, "NZD": 1.3766, "PHP": 54.555, "PLN": 3.1935, "ROL": 27668, "RUB": 27.718, "SEK": 7.0344, "SGD": 1.6514, "SIT": 183.5, "SKK": 30.276, "THB": 39.605, "TRY": 1.3641, "ZAR": 6.0986}}