{"file_metadata": {"source": "Frankfurter Exchange Rates API", "fetch_time": "2026-04-07 22:35:41", "base_currency": "USD", "amount": 1.0, "start_date": "2000-01-01", "end_date": "", "file_date": "2005-04-28", "currency_codes": ["AUD", "BGN", "CAD", "CHF", "CNY", "CYP", "CZK", "DKK", "EEK", "EUR", "GBP", "HKD", "HRK", "HUF", "IDR", "ISK", "JPY", "KRW", "LTL", "LVL", "MTL", "MYR", "NOK", "NZD", "PHP", "PLN", "ROL", "RUB", "SEK", "SGD", "SIT", "SKK", "THB", "TRY", "ZAR"], "count_of_currencies": 35}, "data": {"AUD": 1.2856, "BGN": 1.5156, "CAD": 1.2532, "CHF": 1.1931, "CNY": 8.2765, "CYP": 0.45083, "CZK": 23.65, "DKK": 5.7706, "EEK": 12.1244, "EUR": 0.77489, "GBP": 0.52484, "HKD": 7.799, "HRK": 5.7071, "HUF": 195.34, "IDR": 9580, "ISK": 63.774, "JPY": 105.87, "KRW": 1002.6, "LTL": 2.6756, "LVL": 0.5394, "MTL": 0.33251, "MYR": 3.7999, "NOK": 6.3115, "NZD": 1.3759, "PHP": 54.395, "PLN": 3.3097, "ROL": 28031, "RUB": 27.803, "SEK": 7.0835, "SGD": 1.6466, "SIT": 185.65, "SKK": 30.89, "THB": 39.566, "TRY": 1.3865, "ZAR": 6.1373}}